{"cameraMode":{"drawMode":0,"name":"Shaded","section":"Shading Mode"},"sceneLighting":false,"audioPlay":false,"sceneViewState":{"m_AlwaysRefresh":false,"showFog":true,"showSkybox":false,"showFlares":true,"showImageEffects":true,"showParticleSystems":true,"showVisualEffectGraphs":true,"m_FxEnabled":true},"in2DMode":false,"pivot":{"x":0.19727705419063569,"y":-0.16207313537597657,"z":0.6122888922691345},"rotation":{"x":-0.011069157160818577,"y":0.9887861013412476,"z":-0.11352317035198212,"w":-0.09641249477863312},"size":10.0,"orthographic":false}